{"acc": [0.0, 0.0], "network_size": 8078, "b_mse": [0.1172, 0.1172], "runtime": 61.90781807899475, "alpha_mse": [0.0, 0.0], "d_mse": [0.8456, 0.8456], "adv_type": "random_pgd", "dataset": "facebook", "sample_size": 1, "test_ratio": 0.3, "T": 10, "prob_mse": [0.1135, 0.1135], "realization": 0, "beta_mse": [0.0, 0.0], "attack_edge": 10000, "u_mse": [0.0372, 0.0372], "gamma": 0.0, "swap_ratio": 0.01}
{"acc": [0.0, 0.0], "network_size": 8078, "b_mse": [0.1164, 0.1164], "runtime": 79.1177339553833, "alpha_mse": [0.0, 0.0], "d_mse": [0.8462, 0.8462], "adv_type": "random_pgd", "dataset": "facebook", "sample_size": 1, "test_ratio": 0.3, "T": 10, "prob_mse": [0.1127, 0.1127], "realization": 5, "beta_mse": [0.0, 0.0], "attack_edge": 10000, "u_mse": [0.0374, 0.0374], "gamma": 0.0, "swap_ratio": 0.01}
{"acc": [0.0, 0.0], "network_size": 8078, "b_mse": [0.4127, 0.4127], "runtime": 81.85127592086792, "alpha_mse": [0.0, 0.0], "d_mse": [-0.2243, -0.2243], "adv_type": "random_pgd", "dataset": "facebook", "sample_size": 1, "test_ratio": 0.3, "T": 10, "prob_mse": [0.3947, 0.3947], "realization": 0, "beta_mse": [0.0, 0.0], "attack_edge": 10000, "u_mse": [0.8116, 0.8116], "gamma": 0.01, "swap_ratio": 0.01}
{"acc": [0.0, 0.0], "network_size": 8078, "b_mse": [0.4088, 0.4088], "runtime": 78.43256998062134, "alpha_mse": [0.0, 0.0], "d_mse": [-0.2209, -0.2209], "adv_type": "random_pgd", "dataset": "facebook", "sample_size": 1, "test_ratio": 0.3, "T": 10, "prob_mse": [0.3943, 0.3943], "realization": 5, "beta_mse": [0.0, 0.0], "attack_edge": 10000, "u_mse": [0.8121, 0.8121], "gamma": 0.01, "swap_ratio": 0.01}
{"acc": [0.0, 0.0], "network_size": 8078, "b_mse": [0.412, 0.412], "runtime": 81.3766598701477, "alpha_mse": [0.0, 0.0], "d_mse": [-0.2261, -0.2261], "adv_type": "random_pgd", "dataset": "facebook", "sample_size": 1, "test_ratio": 0.3, "T": 10, "prob_mse": [0.3951, 0.3951], "realization": 0, "beta_mse": [0.0, 0.0], "attack_edge": 10000, "u_mse": [0.8141, 0.8141], "gamma": 0.03, "swap_ratio": 0.01}
{"acc": [0.0, 0.0], "network_size": 8078, "b_mse": [0.4086, 0.4086], "runtime": 78.3987820148468, "alpha_mse": [0.0, 0.0], "d_mse": [-0.2235, -0.2235], "adv_type": "random_pgd", "dataset": "facebook", "sample_size": 1, "test_ratio": 0.3, "T": 10, "prob_mse": [0.3945, 0.3945], "realization": 5, "beta_mse": [0.0, 0.0], "attack_edge": 10000, "u_mse": [0.8149, 0.8149], "gamma": 0.03, "swap_ratio": 0.01}
{"acc": [0.0, 0.0], "network_size": 8078, "b_mse": [0.4128, 0.4128], "runtime": 81.7147569656372, "alpha_mse": [0.0, 0.0], "d_mse": [-0.2251, -0.2251], "adv_type": "random_pgd", "dataset": "facebook", "sample_size": 1, "test_ratio": 0.3, "T": 10, "prob_mse": [0.3944, 0.3944], "realization": 0, "beta_mse": [0.0, 0.0], "attack_edge": 10000, "u_mse": [0.8123, 0.8123], "gamma": 0.05, "swap_ratio": 0.01}
{"acc": [0.0, 0.0], "network_size": 8078, "b_mse": [0.4092, 0.4092], "runtime": 77.9651129245758, "alpha_mse": [0.0, 0.0], "d_mse": [-0.2215, -0.2215], "adv_type": "random_pgd", "dataset": "facebook", "sample_size": 1, "test_ratio": 0.3, "T": 10, "prob_mse": [0.395, 0.395], "realization": 5, "beta_mse": [0.0, 0.0], "attack_edge": 10000, "u_mse": [0.8123, 0.8123], "gamma": 0.05, "swap_ratio": 0.01}
{"acc": [0.0, 0.0], "network_size": 8078, "b_mse": [0.4124, 0.4124], "runtime": 81.02356505393982, "alpha_mse": [0.0, 0.0], "d_mse": [-0.2258, -0.2258], "adv_type": "random_pgd", "dataset": "facebook", "sample_size": 1, "test_ratio": 0.3, "T": 10, "prob_mse": [0.3953, 0.3953], "realization": 0, "beta_mse": [0.0, 0.0], "attack_edge": 10000, "u_mse": [0.8134, 0.8134], "gamma": 0.07, "swap_ratio": 0.01}
{"acc": [0.0, 0.0], "network_size": 8078, "b_mse": [0.409, 0.409], "runtime": 77.56765294075012, "alpha_mse": [0.0, 0.0], "d_mse": [-0.2236, -0.2236], "adv_type": "random_pgd", "dataset": "facebook", "sample_size": 1, "test_ratio": 0.3, "T": 10, "prob_mse": [0.3949, 0.3949], "realization": 5, "beta_mse": [0.0, 0.0], "attack_edge": 10000, "u_mse": [0.8146, 0.8146], "gamma": 0.07, "swap_ratio": 0.01}
{"acc": [0.0, 0.0], "network_size": 8078, "b_mse": [0.4126, 0.4126], "runtime": 80.70333313941956, "alpha_mse": [0.0, 0.0], "d_mse": [-0.2236, -0.2236], "adv_type": "random_pgd", "dataset": "facebook", "sample_size": 1, "test_ratio": 0.3, "T": 10, "prob_mse": [0.3949, 0.3949], "realization": 0, "beta_mse": [0.0, 0.0], "attack_edge": 10000, "u_mse": [0.811, 0.811], "gamma": 0.09, "swap_ratio": 0.01}
{"acc": [0.0, 0.0], "network_size": 8078, "b_mse": [0.4092, 0.4092], "runtime": 77.32443189620972, "alpha_mse": [0.0, 0.0], "d_mse": [-0.2224, -0.2224], "adv_type": "random_pgd", "dataset": "facebook", "sample_size": 1, "test_ratio": 0.3, "T": 10, "prob_mse": [0.395, 0.395], "realization": 5, "beta_mse": [0.0, 0.0], "attack_edge": 10000, "u_mse": [0.8132, 0.8132], "gamma": 0.09, "swap_ratio": 0.01}
{"acc": [0.0, 0.0], "network_size": 8078, "b_mse": [0.4128, 0.4128], "runtime": 80.43557286262512, "alpha_mse": [0.0, 0.0], "d_mse": [-0.2273, -0.2273], "adv_type": "random_pgd", "dataset": "facebook", "sample_size": 1, "test_ratio": 0.3, "T": 10, "prob_mse": [0.395, 0.395], "realization": 0, "beta_mse": [0.0, 0.0], "attack_edge": 10000, "u_mse": [0.8145, 0.8145], "gamma": 0.2, "swap_ratio": 0.01}
{"acc": [0.0, 0.0], "network_size": 8078, "b_mse": [0.4092, 0.4092], "runtime": 77.26464796066284, "alpha_mse": [0.0, 0.0], "d_mse": [-0.2264, -0.2264], "adv_type": "random_pgd", "dataset": "facebook", "sample_size": 1, "test_ratio": 0.3, "T": 10, "prob_mse": [0.3949, 0.3949], "realization": 5, "beta_mse": [0.0, 0.0], "attack_edge": 10000, "u_mse": [0.8172, 0.8172], "gamma": 0.2, "swap_ratio": 0.01}
{"acc": [0.0, 0.0], "network_size": 8078, "b_mse": [0.4124, 0.4124], "runtime": 80.57616400718689, "alpha_mse": [0.0, 0.0], "d_mse": [-0.2251, -0.2251], "adv_type": "random_pgd", "dataset": "facebook", "sample_size": 1, "test_ratio": 0.3, "T": 10, "prob_mse": [0.3946, 0.3946], "realization": 0, "beta_mse": [0.0, 0.0], "attack_edge": 10000, "u_mse": [0.8127, 0.8127], "gamma": 0.3, "swap_ratio": 0.01}
{"acc": [0.0, 0.0], "network_size": 8078, "b_mse": [0.4093, 0.4093], "runtime": 76.47674202919006, "alpha_mse": [0.0, 0.0], "d_mse": [-0.2224, -0.2224], "adv_type": "random_pgd", "dataset": "facebook", "sample_size": 1, "test_ratio": 0.3, "T": 10, "prob_mse": [0.395, 0.395], "realization": 5, "beta_mse": [0.0, 0.0], "attack_edge": 10000, "u_mse": [0.8131, 0.8131], "gamma": 0.3, "swap_ratio": 0.01}
{"acc": [0.0, 0.0], "network_size": 8078, "b_mse": [0.4128, 0.4128], "runtime": 79.6042709350586, "alpha_mse": [0.0, 0.0], "d_mse": [-0.2232, -0.2232], "adv_type": "random_pgd", "dataset": "facebook", "sample_size": 1, "test_ratio": 0.3, "T": 10, "prob_mse": [0.3946, 0.3946], "realization": 0, "beta_mse": [0.0, 0.0], "attack_edge": 10000, "u_mse": [0.8104, 0.8104], "gamma": 0.4, "swap_ratio": 0.01}
{"acc": [0.0, 0.0], "network_size": 8078, "b_mse": [0.4099, 0.4099], "runtime": 76.84775900840759, "alpha_mse": [0.0, 0.0], "d_mse": [-0.221, -0.221], "adv_type": "random_pgd", "dataset": "facebook", "sample_size": 1, "test_ratio": 0.3, "T": 10, "prob_mse": [0.3951, 0.3951], "realization": 5, "beta_mse": [0.0, 0.0], "attack_edge": 10000, "u_mse": [0.8111, 0.8111], "gamma": 0.4, "swap_ratio": 0.01}
{"acc": [0.0, 0.0], "network_size": 8078, "b_mse": [0.4122, 0.4122], "runtime": 80.0959198474884, "alpha_mse": [0.0, 0.0], "d_mse": [-0.2239, -0.2239], "adv_type": "random_pgd", "dataset": "facebook", "sample_size": 1, "test_ratio": 0.3, "T": 10, "prob_mse": [0.3947, 0.3947], "realization": 0, "beta_mse": [0.0, 0.0], "attack_edge": 10000, "u_mse": [0.8117, 0.8117], "gamma": 0.5, "swap_ratio": 0.01}
{"acc": [0.0, 0.0], "network_size": 8078, "b_mse": [0.4082, 0.4082], "runtime": 77.05750107765198, "alpha_mse": [0.0, 0.0], "d_mse": [-0.2216, -0.2216], "adv_type": "random_pgd", "dataset": "facebook", "sample_size": 1, "test_ratio": 0.3, "T": 10, "prob_mse": [0.3947, 0.3947], "realization": 5, "beta_mse": [0.0, 0.0], "attack_edge": 10000, "u_mse": [0.8134, 0.8134], "gamma": 0.5, "swap_ratio": 0.01}
{"acc": [0.0, 0.0], "network_size": 8078, "b_mse": [0.1132, 0.1132], "runtime": 80.54479908943176, "alpha_mse": [0.0, 0.0], "d_mse": [0.8491, 0.8491], "adv_type": "random_pgd", "dataset": "facebook", "sample_size": 1, "test_ratio": 0.3, "T": 10, "prob_mse": [0.1093, 0.1093], "realization": 1, "beta_mse": [0.0, 0.0], "attack_edge": 10000, "u_mse": [0.0377, 0.0377], "gamma": 0.0, "swap_ratio": 0.01}
{"acc": [0.0, 0.0], "network_size": 8078, "b_mse": [0.112, 0.112], "runtime": 75.33042693138123, "alpha_mse": [0.0, 0.0], "d_mse": [0.8503, 0.8503], "adv_type": "random_pgd", "dataset": "facebook", "sample_size": 1, "test_ratio": 0.3, "T": 10, "prob_mse": [0.1088, 0.1088], "realization": 6, "beta_mse": [0.0, 0.0], "attack_edge": 10000, "u_mse": [0.0377, 0.0377], "gamma": 0.0, "swap_ratio": 0.01}
{"acc": [0.0, 0.0], "network_size": 8078, "b_mse": [0.4116, 0.4116], "runtime": 79.4621970653534, "alpha_mse": [0.0, 0.0], "d_mse": [-0.2161, -0.2161], "adv_type": "random_pgd", "dataset": "facebook", "sample_size": 1, "test_ratio": 0.3, "T": 10, "prob_mse": [0.3904, 0.3904], "realization": 1, "beta_mse": [0.0, 0.0], "attack_edge": 10000, "u_mse": [0.8045, 0.8045], "gamma": 0.01, "swap_ratio": 0.01}
{"acc": [0.0, 0.0], "network_size": 8078, "b_mse": [0.4093, 0.4093], "runtime": 74.28945994377136, "alpha_mse": [0.0, 0.0], "d_mse": [-0.2211, -0.2211], "adv_type": "random_pgd", "dataset": "facebook", "sample_size": 1, "test_ratio": 0.3, "T": 10, "prob_mse": [0.3944, 0.3944], "realization": 6, "beta_mse": [0.0, 0.0], "attack_edge": 10000, "u_mse": [0.8118, 0.8118], "gamma": 0.01, "swap_ratio": 0.01}
{"acc": [0.0, 0.0], "network_size": 8078, "b_mse": [0.412, 0.412], "runtime": 77.87803792953491, "alpha_mse": [0.0, 0.0], "d_mse": [-0.2192, -0.2192], "adv_type": "random_pgd", "dataset": "facebook", "sample_size": 1, "test_ratio": 0.3, "T": 10, "prob_mse": [0.3915, 0.3915], "realization": 1, "beta_mse": [0.0, 0.0], "attack_edge": 10000, "u_mse": [0.8072, 0.8072], "gamma": 0.03, "swap_ratio": 0.01}
{"acc": [0.0, 0.0], "network_size": 8078, "b_mse": [0.4086, 0.4086], "runtime": 74.80467414855957, "alpha_mse": [0.0, 0.0], "d_mse": [-0.2218, -0.2218], "adv_type": "random_pgd", "dataset": "facebook", "sample_size": 1, "test_ratio": 0.3, "T": 10, "prob_mse": [0.3944, 0.3944], "realization": 6, "beta_mse": [0.0, 0.0], "attack_edge": 10000, "u_mse": [0.8132, 0.8132], "gamma": 0.03, "swap_ratio": 0.01}
{"acc": [0.0, 0.0], "network_size": 8078, "b_mse": [0.4121, 0.4121], "runtime": 78.44661903381348, "alpha_mse": [0.0, 0.0], "d_mse": [-0.2182, -0.2182], "adv_type": "random_pgd", "dataset": "facebook", "sample_size": 1, "test_ratio": 0.3, "T": 10, "prob_mse": [0.3912, 0.3912], "realization": 1, "beta_mse": [0.0, 0.0], "attack_edge": 10000, "u_mse": [0.8061, 0.8061], "gamma": 0.05, "swap_ratio": 0.01}
{"acc": [0.0, 0.0], "network_size": 8078, "b_mse": [0.4095, 0.4095], "runtime": 73.83252596855164, "alpha_mse": [0.0, 0.0], "d_mse": [-0.2229, -0.2229], "adv_type": "random_pgd", "dataset": "facebook", "sample_size": 1, "test_ratio": 0.3, "T": 10, "prob_mse": [0.3944, 0.3944], "realization": 6, "beta_mse": [0.0, 0.0], "attack_edge": 10000, "u_mse": [0.8134, 0.8134], "gamma": 0.05, "swap_ratio": 0.01}
{"acc": [0.0, 0.0], "network_size": 8078, "b_mse": [0.4115, 0.4115], "runtime": 77.32109713554382, "alpha_mse": [0.0, 0.0], "d_mse": [-0.2169, -0.2169], "adv_type": "random_pgd", "dataset": "facebook", "sample_size": 1, "test_ratio": 0.3, "T": 10, "prob_mse": [0.3908, 0.3908], "realization": 1, "beta_mse": [0.0, 0.0], "attack_edge": 10000, "u_mse": [0.8054, 0.8054], "gamma": 0.07, "swap_ratio": 0.01}
{"acc": [0.0, 0.0], "network_size": 8078, "b_mse": [0.4087, 0.4087], "runtime": 73.148264169693, "alpha_mse": [0.0, 0.0], "d_mse": [-0.2209, -0.2209], "adv_type": "random_pgd", "dataset": "facebook", "sample_size": 1, "test_ratio": 0.3, "T": 10, "prob_mse": [0.394, 0.394], "realization": 6, "beta_mse": [0.0, 0.0], "attack_edge": 10000, "u_mse": [0.8122, 0.8122], "gamma": 0.07, "swap_ratio": 0.01}
{"acc": [0.0, 0.0], "network_size": 8078, "b_mse": [0.4123, 0.4123], "runtime": 77.57918095588684, "alpha_mse": [0.0, 0.0], "d_mse": [-0.2144, -0.2144], "adv_type": "random_pgd", "dataset": "facebook", "sample_size": 1, "test_ratio": 0.3, "T": 10, "prob_mse": [0.3906, 0.3906], "realization": 1, "beta_mse": [0.0, 0.0], "attack_edge": 10000, "u_mse": [0.8021, 0.8021], "gamma": 0.09, "swap_ratio": 0.01}
{"acc": [0.0, 0.0], "network_size": 8078, "b_mse": [0.4103, 0.4103], "runtime": 72.2747540473938, "alpha_mse": [0.0, 0.0], "d_mse": [-0.2179, -0.2179], "adv_type": "random_pgd", "dataset": "facebook", "sample_size": 1, "test_ratio": 0.3, "T": 10, "prob_mse": [0.3938, 0.3938], "realization": 6, "beta_mse": [0.0, 0.0], "attack_edge": 10000, "u_mse": [0.8076, 0.8076], "gamma": 0.09, "swap_ratio": 0.01}
{"acc": [0.0, 0.0], "network_size": 8078, "b_mse": [0.4117, 0.4117], "runtime": 76.34488296508789, "alpha_mse": [0.0, 0.0], "d_mse": [-0.2195, -0.2195], "adv_type": "random_pgd", "dataset": "facebook", "sample_size": 1, "test_ratio": 0.3, "T": 10, "prob_mse": [0.3911, 0.3911], "realization": 1, "beta_mse": [0.0, 0.0], "attack_edge": 10000, "u_mse": [0.8078, 0.8078], "gamma": 0.2, "swap_ratio": 0.01}
{"acc": [0.0, 0.0], "network_size": 8078, "b_mse": [0.4092, 0.4092], "runtime": 71.06567287445068, "alpha_mse": [0.0, 0.0], "d_mse": [-0.2242, -0.2242], "adv_type": "random_pgd", "dataset": "facebook", "sample_size": 1, "test_ratio": 0.3, "T": 10, "prob_mse": [0.3943, 0.3943], "realization": 6, "beta_mse": [0.0, 0.0], "attack_edge": 10000, "u_mse": [0.815, 0.815], "gamma": 0.2, "swap_ratio": 0.01}
{"acc": [0.0, 0.0], "network_size": 8078, "b_mse": [0.4121, 0.4121], "runtime": 75.69308495521545, "alpha_mse": [0.0, 0.0], "d_mse": [-0.2189, -0.2189], "adv_type": "random_pgd", "dataset": "facebook", "sample_size": 1, "test_ratio": 0.3, "T": 10, "prob_mse": [0.3911, 0.3911], "realization": 1, "beta_mse": [0.0, 0.0], "attack_edge": 10000, "u_mse": [0.8068, 0.8068], "gamma": 0.3, "swap_ratio": 0.01}
{"acc": [0.0, 0.0], "network_size": 8078, "b_mse": [0.4094, 0.4094], "runtime": 70.76560306549072, "alpha_mse": [0.0, 0.0], "d_mse": [-0.2228, -0.2228], "adv_type": "random_pgd", "dataset": "facebook", "sample_size": 1, "test_ratio": 0.3, "T": 10, "prob_mse": [0.3946, 0.3946], "realization": 6, "beta_mse": [0.0, 0.0], "attack_edge": 10000, "u_mse": [0.8134, 0.8134], "gamma": 0.3, "swap_ratio": 0.01}
{"acc": [0.0, 0.0], "network_size": 8078, "b_mse": [0.4117, 0.4117], "runtime": 74.77953314781189, "alpha_mse": [0.0, 0.0], "d_mse": [-0.2149, -0.2149], "adv_type": "random_pgd", "dataset": "facebook", "sample_size": 1, "test_ratio": 0.3, "T": 10, "prob_mse": [0.3899, 0.3899], "realization": 1, "beta_mse": [0.0, 0.0], "attack_edge": 10000, "u_mse": [0.8032, 0.8032], "gamma": 0.4, "swap_ratio": 0.01}
{"acc": [0.0, 0.0], "network_size": 8078, "b_mse": [0.4094, 0.4094], "runtime": 69.80022501945496, "alpha_mse": [0.0, 0.0], "d_mse": [-0.2239, -0.2239], "adv_type": "random_pgd", "dataset": "facebook", "sample_size": 1, "test_ratio": 0.3, "T": 10, "prob_mse": [0.3944, 0.3944], "realization": 6, "beta_mse": [0.0, 0.0], "attack_edge": 10000, "u_mse": [0.8145, 0.8145], "gamma": 0.4, "swap_ratio": 0.01}
{"acc": [0.0, 0.0], "network_size": 8078, "b_mse": [0.4121, 0.4121], "runtime": 73.73980689048767, "alpha_mse": [0.0, 0.0], "d_mse": [-0.218, -0.218], "adv_type": "random_pgd", "dataset": "facebook", "sample_size": 1, "test_ratio": 0.3, "T": 10, "prob_mse": [0.3909, 0.3909], "realization": 1, "beta_mse": [0.0, 0.0], "attack_edge": 10000, "u_mse": [0.8059, 0.8059], "gamma": 0.5, "swap_ratio": 0.01}
{"acc": [0.0, 0.0], "network_size": 8078, "b_mse": [0.4095, 0.4095], "runtime": 70.81307911872864, "alpha_mse": [0.0, 0.0], "d_mse": [-0.2225, -0.2225], "adv_type": "random_pgd", "dataset": "facebook", "sample_size": 1, "test_ratio": 0.3, "T": 10, "prob_mse": [0.3944, 0.3944], "realization": 6, "beta_mse": [0.0, 0.0], "attack_edge": 10000, "u_mse": [0.813, 0.813], "gamma": 0.5, "swap_ratio": 0.01}
{"acc": [0.0, 0.0], "network_size": 8078, "b_mse": [0.1106, 0.1106], "runtime": 74.01564383506775, "alpha_mse": [0.0, 0.0], "d_mse": [0.8522, 0.8522], "adv_type": "random_pgd", "dataset": "facebook", "sample_size": 1, "test_ratio": 0.3, "T": 10, "prob_mse": [0.1075, 0.1075], "realization": 2, "beta_mse": [0.0, 0.0], "attack_edge": 10000, "u_mse": [0.0372, 0.0372], "gamma": 0.0, "swap_ratio": 0.01}
{"acc": [0.0, 0.0], "network_size": 8078, "b_mse": [0.1177, 0.1177], "runtime": 69.45358300209045, "alpha_mse": [0.0, 0.0], "d_mse": [0.8443, 0.8443], "adv_type": "random_pgd", "dataset": "facebook", "sample_size": 1, "test_ratio": 0.3, "T": 10, "prob_mse": [0.1143, 0.1143], "realization": 7, "beta_mse": [0.0, 0.0], "attack_edge": 10000, "u_mse": [0.038, 0.038], "gamma": 0.0, "swap_ratio": 0.01}
{"acc": [0.0, 0.0], "network_size": 8078, "b_mse": [0.4071, 0.4071], "runtime": 74.5420708656311, "alpha_mse": [0.0, 0.0], "d_mse": [-0.2262, -0.2262], "adv_type": "random_pgd", "dataset": "facebook", "sample_size": 1, "test_ratio": 0.3, "T": 10, "prob_mse": [0.3949, 0.3949], "realization": 2, "beta_mse": [0.0, 0.0], "attack_edge": 10000, "u_mse": [0.8191, 0.8191], "gamma": 0.01, "swap_ratio": 0.01}
{"acc": [0.0, 0.0], "network_size": 8078, "b_mse": [0.4135, 0.4135], "runtime": 68.39583897590637, "alpha_mse": [0.0, 0.0], "d_mse": [-0.228, -0.228], "adv_type": "random_pgd", "dataset": "facebook", "sample_size": 1, "test_ratio": 0.3, "T": 10, "prob_mse": [0.3935, 0.3935], "realization": 7, "beta_mse": [0.0, 0.0], "attack_edge": 10000, "u_mse": [0.8145, 0.8145], "gamma": 0.01, "swap_ratio": 0.01}
{"acc": [0.0, 0.0], "network_size": 8078, "b_mse": [0.4072, 0.4072], "runtime": 72.07366299629211, "alpha_mse": [0.0, 0.0], "d_mse": [-0.2264, -0.2264], "adv_type": "random_pgd", "dataset": "facebook", "sample_size": 1, "test_ratio": 0.3, "T": 10, "prob_mse": [0.3947, 0.3947], "realization": 2, "beta_mse": [0.0, 0.0], "attack_edge": 10000, "u_mse": [0.8192, 0.8192], "gamma": 0.03, "swap_ratio": 0.01}
{"acc": [0.0, 0.0], "network_size": 8078, "b_mse": [0.4135, 0.4135], "runtime": 69.75814914703369, "alpha_mse": [0.0, 0.0], "d_mse": [-0.2274, -0.2274], "adv_type": "random_pgd", "dataset": "facebook", "sample_size": 1, "test_ratio": 0.3, "T": 10, "prob_mse": [0.3933, 0.3933], "realization": 7, "beta_mse": [0.0, 0.0], "attack_edge": 10000, "u_mse": [0.8139, 0.8139], "gamma": 0.03, "swap_ratio": 0.01}
{"acc": [0.0, 0.0], "network_size": 8078, "b_mse": [0.4072, 0.4072], "runtime": 72.69488310813904, "alpha_mse": [0.0, 0.0], "d_mse": [-0.2259, -0.2259], "adv_type": "random_pgd", "dataset": "facebook", "sample_size": 1, "test_ratio": 0.3, "T": 10, "prob_mse": [0.3947, 0.3947], "realization": 2, "beta_mse": [0.0, 0.0], "attack_edge": 10000, "u_mse": [0.8187, 0.8187], "gamma": 0.05, "swap_ratio": 0.01}
{"acc": [0.0, 0.0], "network_size": 8078, "b_mse": [0.414, 0.414], "runtime": 68.64365196228027, "alpha_mse": [0.0, 0.0], "d_mse": [-0.2258, -0.2258], "adv_type": "random_pgd", "dataset": "facebook", "sample_size": 1, "test_ratio": 0.3, "T": 10, "prob_mse": [0.3933, 0.3933], "realization": 7, "beta_mse": [0.0, 0.0], "attack_edge": 10000, "u_mse": [0.8118, 0.8118], "gamma": 0.05, "swap_ratio": 0.01}
{"acc": [0.0, 0.0], "network_size": 8078, "b_mse": [0.407, 0.407], "runtime": 72.81980395317078, "alpha_mse": [0.0, 0.0], "d_mse": [-0.2208, -0.2208], "adv_type": "random_pgd", "dataset": "facebook", "sample_size": 1, "test_ratio": 0.3, "T": 10, "prob_mse": [0.3949, 0.3949], "realization": 2, "beta_mse": [0.0, 0.0], "attack_edge": 10000, "u_mse": [0.8138, 0.8138], "gamma": 0.07, "swap_ratio": 0.01}
{"acc": [0.0, 0.0], "network_size": 8078, "b_mse": [0.4136, 0.4136], "runtime": 69.87392902374268, "alpha_mse": [0.0, 0.0], "d_mse": [-0.2217, -0.2217], "adv_type": "random_pgd", "dataset": "facebook", "sample_size": 1, "test_ratio": 0.3, "T": 10, "prob_mse": [0.3928, 0.3928], "realization": 7, "beta_mse": [0.0, 0.0], "attack_edge": 10000, "u_mse": [0.8081, 0.8081], "gamma": 0.07, "swap_ratio": 0.01}
{"acc": [0.0, 0.0], "network_size": 8078, "b_mse": [0.4066, 0.4066], "runtime": 72.4113450050354, "alpha_mse": [0.0, 0.0], "d_mse": [-0.2208, -0.2208], "adv_type": "random_pgd", "dataset": "facebook", "sample_size": 1, "test_ratio": 0.3, "T": 10, "prob_mse": [0.3949, 0.3949], "realization": 2, "beta_mse": [0.0, 0.0], "attack_edge": 10000, "u_mse": [0.8142, 0.8142], "gamma": 0.09, "swap_ratio": 0.01}
{"acc": [0.0, 0.0], "network_size": 8078, "b_mse": [0.4136, 0.4136], "runtime": 68.30918788909912, "alpha_mse": [0.0, 0.0], "d_mse": [-0.223, -0.223], "adv_type": "random_pgd", "dataset": "facebook", "sample_size": 1, "test_ratio": 0.3, "T": 10, "prob_mse": [0.3933, 0.3933], "realization": 7, "beta_mse": [0.0, 0.0], "attack_edge": 10000, "u_mse": [0.8094, 0.8094], "gamma": 0.09, "swap_ratio": 0.01}
{"acc": [0.0, 0.0], "network_size": 8078, "b_mse": [0.4063, 0.4063], "runtime": 70.7205958366394, "alpha_mse": [0.0, 0.0], "d_mse": [-0.2204, -0.2204], "adv_type": "random_pgd", "dataset": "facebook", "sample_size": 1, "test_ratio": 0.3, "T": 10, "prob_mse": [0.3944, 0.3944], "realization": 2, "beta_mse": [0.0, 0.0], "attack_edge": 10000, "u_mse": [0.8141, 0.8141], "gamma": 0.2, "swap_ratio": 0.01}
{"acc": [0.0, 0.0], "network_size": 8078, "b_mse": [0.4136, 0.4136], "runtime": 70.00480699539185, "alpha_mse": [0.0, 0.0], "d_mse": [-0.2226, -0.2226], "adv_type": "random_pgd", "dataset": "facebook", "sample_size": 1, "test_ratio": 0.3, "T": 10, "prob_mse": [0.393, 0.393], "realization": 7, "beta_mse": [0.0, 0.0], "attack_edge": 10000, "u_mse": [0.809, 0.809], "gamma": 0.2, "swap_ratio": 0.01}
{"acc": [0.0, 0.0], "network_size": 8078, "b_mse": [0.4072, 0.4072], "runtime": 70.84314608573914, "alpha_mse": [0.0, 0.0], "d_mse": [-0.2245, -0.2245], "adv_type": "random_pgd", "dataset": "facebook", "sample_size": 1, "test_ratio": 0.3, "T": 10, "prob_mse": [0.3949, 0.3949], "realization": 2, "beta_mse": [0.0, 0.0], "attack_edge": 10000, "u_mse": [0.8173, 0.8173], "gamma": 0.3, "swap_ratio": 0.01}
{"acc": [0.0, 0.0], "network_size": 8078, "b_mse": [0.4138, 0.4138], "runtime": 69.8613851070404, "alpha_mse": [0.0, 0.0], "d_mse": [-0.2243, -0.2243], "adv_type": "random_pgd", "dataset": "facebook", "sample_size": 1, "test_ratio": 0.3, "T": 10, "prob_mse": [0.3934, 0.3934], "realization": 7, "beta_mse": [0.0, 0.0], "attack_edge": 10000, "u_mse": [0.8105, 0.8105], "gamma": 0.3, "swap_ratio": 0.01}
{"acc": [0.0, 0.0], "network_size": 8078, "b_mse": [0.4076, 0.4076], "runtime": 70.09840798377991, "alpha_mse": [0.0, 0.0], "d_mse": [-0.2174, -0.2174], "adv_type": "random_pgd", "dataset": "facebook", "sample_size": 1, "test_ratio": 0.3, "T": 10, "prob_mse": [0.3937, 0.3937], "realization": 2, "beta_mse": [0.0, 0.0], "attack_edge": 10000, "u_mse": [0.8098, 0.8098], "gamma": 0.4, "swap_ratio": 0.01}
{"acc": [0.0, 0.0], "network_size": 8078, "b_mse": [0.4141, 0.4141], "runtime": 69.47988295555115, "alpha_mse": [0.0, 0.0], "d_mse": [-0.2178, -0.2178], "adv_type": "random_pgd", "dataset": "facebook", "sample_size": 1, "test_ratio": 0.3, "T": 10, "prob_mse": [0.3915, 0.3915], "realization": 7, "beta_mse": [0.0, 0.0], "attack_edge": 10000, "u_mse": [0.8037, 0.8037], "gamma": 0.4, "swap_ratio": 0.01}
{"acc": [0.0, 0.0], "network_size": 8078, "b_mse": [0.4064, 0.4064], "runtime": 69.79747009277344, "alpha_mse": [0.0, 0.0], "d_mse": [-0.2205, -0.2205], "adv_type": "random_pgd", "dataset": "facebook", "sample_size": 1, "test_ratio": 0.3, "T": 10, "prob_mse": [0.3944, 0.3944], "realization": 2, "beta_mse": [0.0, 0.0], "attack_edge": 10000, "u_mse": [0.8141, 0.8141], "gamma": 0.5, "swap_ratio": 0.01}
{"acc": [0.0, 0.0], "network_size": 8078, "b_mse": [0.4136, 0.4136], "runtime": 70.61277198791504, "alpha_mse": [0.0, 0.0], "d_mse": [-0.2221, -0.2221], "adv_type": "random_pgd", "dataset": "facebook", "sample_size": 1, "test_ratio": 0.3, "T": 10, "prob_mse": [0.393, 0.393], "realization": 7, "beta_mse": [0.0, 0.0], "attack_edge": 10000, "u_mse": [0.8085, 0.8085], "gamma": 0.5, "swap_ratio": 0.01}
{"acc": [0.0, 0.0], "network_size": 8078, "b_mse": [0.1143, 0.1143], "runtime": 70.11160087585449, "alpha_mse": [0.0, 0.0], "d_mse": [0.8491, 0.8491], "adv_type": "random_pgd", "dataset": "facebook", "sample_size": 1, "test_ratio": 0.3, "T": 10, "prob_mse": [0.1106, 0.1106], "realization": 3, "beta_mse": [0.0, 0.0], "attack_edge": 10000, "u_mse": [0.0366, 0.0366], "gamma": 0.0, "swap_ratio": 0.01}
{"acc": [0.0, 0.0], "network_size": 8078, "b_mse": [0.116, 0.116], "runtime": 69.15675497055054, "alpha_mse": [0.0, 0.0], "d_mse": [0.8467, 0.8467], "adv_type": "random_pgd", "dataset": "facebook", "sample_size": 1, "test_ratio": 0.3, "T": 10, "prob_mse": [0.1118, 0.1118], "realization": 8, "beta_mse": [0.0, 0.0], "attack_edge": 10000, "u_mse": [0.0373, 0.0373], "gamma": 0.0, "swap_ratio": 0.01}
{"acc": [0.0, 0.0], "network_size": 8078, "b_mse": [0.4077, 0.4077], "runtime": 69.11128091812134, "alpha_mse": [0.0, 0.0], "d_mse": [-0.2212, -0.2212], "adv_type": "random_pgd", "dataset": "facebook", "sample_size": 1, "test_ratio": 0.3, "T": 10, "prob_mse": [0.3943, 0.3943], "realization": 3, "beta_mse": [0.0, 0.0], "attack_edge": 10000, "u_mse": [0.8135, 0.8135], "gamma": 0.01, "swap_ratio": 0.01}
{"acc": [0.0, 0.0], "network_size": 8078, "b_mse": [0.4132, 0.4132], "runtime": 70.89262104034424, "alpha_mse": [0.0, 0.0], "d_mse": [-0.2375, -0.2375], "adv_type": "random_pgd", "dataset": "facebook", "sample_size": 1, "test_ratio": 0.3, "T": 10, "prob_mse": [0.3951, 0.3951], "realization": 8, "beta_mse": [0.0, 0.0], "attack_edge": 10000, "u_mse": [0.8243, 0.8243], "gamma": 0.01, "swap_ratio": 0.01}
{"acc": [0.0, 0.0], "network_size": 8078, "b_mse": [0.4069, 0.4069], "runtime": 68.02908897399902, "alpha_mse": [0.0, 0.0], "d_mse": [-0.2161, -0.2161], "adv_type": "random_pgd", "dataset": "facebook", "sample_size": 1, "test_ratio": 0.3, "T": 10, "prob_mse": [0.3921, 0.3921], "realization": 3, "beta_mse": [0.0, 0.0], "attack_edge": 10000, "u_mse": [0.8092, 0.8092], "gamma": 0.03, "swap_ratio": 0.01}
{"acc": [0.0, 0.0], "network_size": 8078, "b_mse": [0.4119, 0.4119], "runtime": 69.99252200126648, "alpha_mse": [0.0, 0.0], "d_mse": [-0.225, -0.225], "adv_type": "random_pgd", "dataset": "facebook", "sample_size": 1, "test_ratio": 0.3, "T": 10, "prob_mse": [0.3932, 0.3932], "realization": 8, "beta_mse": [0.0, 0.0], "attack_edge": 10000, "u_mse": [0.8131, 0.8131], "gamma": 0.03, "swap_ratio": 0.01}
{"acc": [0.0, 0.0], "network_size": 8078, "b_mse": [0.4075, 0.4075], "runtime": 69.55723214149475, "alpha_mse": [0.0, 0.0], "d_mse": [-0.2201, -0.2201], "adv_type": "random_pgd", "dataset": "facebook", "sample_size": 1, "test_ratio": 0.3, "T": 10, "prob_mse": [0.3942, 0.3942], "realization": 3, "beta_mse": [0.0, 0.0], "attack_edge": 10000, "u_mse": [0.8126, 0.8126], "gamma": 0.05, "swap_ratio": 0.01}
{"acc": [0.0, 0.0], "network_size": 8078, "b_mse": [0.4123, 0.4123], "runtime": 69.32553601264954, "alpha_mse": [0.0, 0.0], "d_mse": [-0.2349, -0.2349], "adv_type": "random_pgd", "dataset": "facebook", "sample_size": 1, "test_ratio": 0.3, "T": 10, "prob_mse": [0.395, 0.395], "realization": 8, "beta_mse": [0.0, 0.0], "attack_edge": 10000, "u_mse": [0.8226, 0.8226], "gamma": 0.05, "swap_ratio": 0.01}
{"acc": [0.0, 0.0], "network_size": 8078, "b_mse": [0.4076, 0.4076], "runtime": 67.8925530910492, "alpha_mse": [0.0, 0.0], "d_mse": [-0.2165, -0.2165], "adv_type": "random_pgd", "dataset": "facebook", "sample_size": 1, "test_ratio": 0.3, "T": 10, "prob_mse": [0.3931, 0.3931], "realization": 3, "beta_mse": [0.0, 0.0], "attack_edge": 10000, "u_mse": [0.8089, 0.8089], "gamma": 0.07, "swap_ratio": 0.01}
{"acc": [0.0, 0.0], "network_size": 8078, "b_mse": [0.413, 0.413], "runtime": 69.3260428905487, "alpha_mse": [0.0, 0.0], "d_mse": [-0.2261, -0.2261], "adv_type": "random_pgd", "dataset": "facebook", "sample_size": 1, "test_ratio": 0.3, "T": 10, "prob_mse": [0.3946, 0.3946], "realization": 8, "beta_mse": [0.0, 0.0], "attack_edge": 10000, "u_mse": [0.8131, 0.8131], "gamma": 0.07, "swap_ratio": 0.01}
{"acc": [0.0, 0.0], "network_size": 8078, "b_mse": [0.4067, 0.4067], "runtime": 70.32591605186462, "alpha_mse": [0.0, 0.0], "d_mse": [-0.2193, -0.2193], "adv_type": "random_pgd", "dataset": "facebook", "sample_size": 1, "test_ratio": 0.3, "T": 10, "prob_mse": [0.3938, 0.3938], "realization": 3, "beta_mse": [0.0, 0.0], "attack_edge": 10000, "u_mse": [0.8126, 0.8126], "gamma": 0.09, "swap_ratio": 0.01}
{"acc": [0.0, 0.0], "network_size": 8078, "b_mse": [0.4116, 0.4116], "runtime": 68.96767902374268, "alpha_mse": [0.0, 0.0], "d_mse": [-0.2303, -0.2303], "adv_type": "random_pgd", "dataset": "facebook", "sample_size": 1, "test_ratio": 0.3, "T": 10, "prob_mse": [0.3948, 0.3948], "realization": 8, "beta_mse": [0.0, 0.0], "attack_edge": 10000, "u_mse": [0.8187, 0.8187], "gamma": 0.09, "swap_ratio": 0.01}
{"acc": [0.0, 0.0], "network_size": 8078, "b_mse": [0.4084, 0.4084], "runtime": 68.44983911514282, "alpha_mse": [0.0, 0.0], "d_mse": [-0.2214, -0.2214], "adv_type": "random_pgd", "dataset": "facebook", "sample_size": 1, "test_ratio": 0.3, "T": 10, "prob_mse": [0.3943, 0.3943], "realization": 3, "beta_mse": [0.0, 0.0], "attack_edge": 10000, "u_mse": [0.813, 0.813], "gamma": 0.2, "swap_ratio": 0.01}
{"acc": [0.0, 0.0], "network_size": 8078, "b_mse": [0.4124, 0.4124], "runtime": 71.66143798828125, "alpha_mse": [0.0, 0.0], "d_mse": [-0.2284, -0.2284], "adv_type": "random_pgd", "dataset": "facebook", "sample_size": 1, "test_ratio": 0.3, "T": 10, "prob_mse": [0.3947, 0.3947], "realization": 8, "beta_mse": [0.0, 0.0], "attack_edge": 10000, "u_mse": [0.816, 0.816], "gamma": 0.2, "swap_ratio": 0.01}
{"acc": [0.0, 0.0], "network_size": 8078, "b_mse": [0.4073, 0.4073], "runtime": 67.1028881072998, "alpha_mse": [0.0, 0.0], "d_mse": [-0.2149, -0.2149], "adv_type": "random_pgd", "dataset": "facebook", "sample_size": 1, "test_ratio": 0.3, "T": 10, "prob_mse": [0.3922, 0.3922], "realization": 3, "beta_mse": [0.0, 0.0], "attack_edge": 10000, "u_mse": [0.8076, 0.8076], "gamma": 0.3, "swap_ratio": 0.01}
{"acc": [0.0, 0.0], "network_size": 8078, "b_mse": [0.4119, 0.4119], "runtime": 69.46514081954956, "alpha_mse": [0.0, 0.0], "d_mse": [-0.2281, -0.2281], "adv_type": "random_pgd", "dataset": "facebook", "sample_size": 1, "test_ratio": 0.3, "T": 10, "prob_mse": [0.395, 0.395], "realization": 8, "beta_mse": [0.0, 0.0], "attack_edge": 10000, "u_mse": [0.8162, 0.8162], "gamma": 0.3, "swap_ratio": 0.01}
{"acc": [0.0, 0.0], "network_size": 8078, "b_mse": [0.408, 0.408], "runtime": 68.74441003799438, "alpha_mse": [0.0, 0.0], "d_mse": [-0.2198, -0.2198], "adv_type": "random_pgd", "dataset": "facebook", "sample_size": 1, "test_ratio": 0.3, "T": 10, "prob_mse": [0.3944, 0.3944], "realization": 3, "beta_mse": [0.0, 0.0], "attack_edge": 10000, "u_mse": [0.8118, 0.8118], "gamma": 0.4, "swap_ratio": 0.01}
{"acc": [0.0, 0.0], "network_size": 8078, "b_mse": [0.4133, 0.4133], "runtime": 69.36987400054932, "alpha_mse": [0.0, 0.0], "d_mse": [-0.2363, -0.2363], "adv_type": "random_pgd", "dataset": "facebook", "sample_size": 1, "test_ratio": 0.3, "T": 10, "prob_mse": [0.3952, 0.3952], "realization": 8, "beta_mse": [0.0, 0.0], "attack_edge": 10000, "u_mse": [0.823, 0.823], "gamma": 0.4, "swap_ratio": 0.01}
{"acc": [0.0, 0.0], "network_size": 8078, "b_mse": [0.4077, 0.4077], "runtime": 69.49928998947144, "alpha_mse": [0.0, 0.0], "d_mse": [-0.2213, -0.2213], "adv_type": "random_pgd", "dataset": "facebook", "sample_size": 1, "test_ratio": 0.3, "T": 10, "prob_mse": [0.3942, 0.3942], "realization": 3, "beta_mse": [0.0, 0.0], "attack_edge": 10000, "u_mse": [0.8136, 0.8136], "gamma": 0.5, "swap_ratio": 0.01}
{"acc": [0.0, 0.0], "network_size": 8078, "b_mse": [0.4116, 0.4116], "runtime": 69.2614529132843, "alpha_mse": [0.0, 0.0], "d_mse": [-0.2301, -0.2301], "adv_type": "random_pgd", "dataset": "facebook", "sample_size": 1, "test_ratio": 0.3, "T": 10, "prob_mse": [0.3948, 0.3948], "realization": 8, "beta_mse": [0.0, 0.0], "attack_edge": 10000, "u_mse": [0.8185, 0.8185], "gamma": 0.5, "swap_ratio": 0.01}
{"acc": [0.0, 0.0], "network_size": 8078, "b_mse": [0.1142, 0.1142], "runtime": 70.26640605926514, "alpha_mse": [0.0, 0.0], "d_mse": [0.8482, 0.8482], "adv_type": "random_pgd", "dataset": "facebook", "sample_size": 1, "test_ratio": 0.3, "T": 10, "prob_mse": [0.1109, 0.1109], "realization": 4, "beta_mse": [0.0, 0.0], "attack_edge": 10000, "u_mse": [0.0376, 0.0376], "gamma": 0.0, "swap_ratio": 0.01}
{"acc": [0.0, 0.0], "network_size": 8078, "b_mse": [0.1144, 0.1144], "runtime": 68.66806197166443, "alpha_mse": [0.0, 0.0], "d_mse": [0.8488, 0.8488], "adv_type": "random_pgd", "dataset": "facebook", "sample_size": 1, "test_ratio": 0.3, "T": 10, "prob_mse": [0.1107, 0.1107], "realization": 9, "beta_mse": [0.0, 0.0], "attack_edge": 10000, "u_mse": [0.0368, 0.0368], "gamma": 0.0, "swap_ratio": 0.01}
{"acc": [0.0, 0.0], "network_size": 8078, "b_mse": [0.409, 0.409], "runtime": 69.8185670375824, "alpha_mse": [0.0, 0.0], "d_mse": [-0.2175, -0.2175], "adv_type": "random_pgd", "dataset": "facebook", "sample_size": 1, "test_ratio": 0.3, "T": 10, "prob_mse": [0.3948, 0.3948], "realization": 4, "beta_mse": [0.0, 0.0], "attack_edge": 10000, "u_mse": [0.8085, 0.8085], "gamma": 0.01, "swap_ratio": 0.01}
{"acc": [0.0, 0.0], "network_size": 8078, "b_mse": [0.4119, 0.4119], "runtime": 68.72183799743652, "alpha_mse": [0.0, 0.0], "d_mse": [-0.2223, -0.2223], "adv_type": "random_pgd", "dataset": "facebook", "sample_size": 1, "test_ratio": 0.3, "T": 10, "prob_mse": [0.394, 0.394], "realization": 9, "beta_mse": [0.0, 0.0], "attack_edge": 10000, "u_mse": [0.8104, 0.8104], "gamma": 0.01, "swap_ratio": 0.01}
{"acc": [0.0, 0.0], "network_size": 8078, "b_mse": [0.4083, 0.4083], "runtime": 68.09099102020264, "alpha_mse": [0.0, 0.0], "d_mse": [-0.2154, -0.2154], "adv_type": "random_pgd", "dataset": "facebook", "sample_size": 1, "test_ratio": 0.3, "T": 10, "prob_mse": [0.3936, 0.3936], "realization": 4, "beta_mse": [0.0, 0.0], "attack_edge": 10000, "u_mse": [0.8071, 0.8071], "gamma": 0.03, "swap_ratio": 0.01}
{"acc": [0.0, 0.0], "network_size": 8078, "b_mse": [0.4113, 0.4113], "runtime": 72.87343716621399, "alpha_mse": [0.0, 0.0], "d_mse": [-0.2219, -0.2219], "adv_type": "random_pgd", "dataset": "facebook", "sample_size": 1, "test_ratio": 0.3, "T": 10, "prob_mse": [0.394, 0.394], "realization": 9, "beta_mse": [0.0, 0.0], "attack_edge": 10000, "u_mse": [0.8106, 0.8106], "gamma": 0.03, "swap_ratio": 0.01}
{"acc": [0.0, 0.0], "network_size": 8078, "b_mse": [0.4122, 0.4122], "runtime": 134.24318504333496, "alpha_mse": [0.0, 0.0], "d_mse": [-0.2239, -0.2239], "adv_type": "random_pgd", "dataset": "facebook", "sample_size": 1, "test_ratio": 0.3, "T": 10, "prob_mse": [0.3947, 0.3947], "realization": 0, "beta_mse": [0.0, 0.0], "attack_edge": 10000, "u_mse": [0.8117, 0.8117], "gamma": 0.01, "swap_ratio": 0.01}
{"acc": [0.0, 0.0], "network_size": 8078, "b_mse": [0.4122, 0.4122], "runtime": 135.37950897216797, "alpha_mse": [0.0, 0.0], "d_mse": [-0.2239, -0.2239], "adv_type": "random_pgd", "dataset": "facebook", "sample_size": 1, "test_ratio": 0.3, "T": 10, "prob_mse": [0.3947, 0.3947], "realization": 0, "beta_mse": [0.0, 0.0], "attack_edge": 10000, "u_mse": [0.8117, 0.8117], "gamma": 0.01, "swap_ratio": 0.01}
{"acc": [0.0, 0.0], "network_size": 8078, "b_mse": [0.4083, 0.4083], "runtime": 68.23728489875793, "alpha_mse": [0.0, 0.0], "d_mse": [-0.223, -0.223], "adv_type": "random_pgd", "dataset": "facebook", "sample_size": 1, "test_ratio": 0.3, "T": 10, "prob_mse": [0.3952, 0.3952], "realization": 4, "beta_mse": [0.0, 0.0], "attack_edge": 10000, "u_mse": [0.8147, 0.8147], "gamma": 0.05, "swap_ratio": 0.01}
{"acc": [0.0, 0.0], "network_size": 8078, "b_mse": [0.4114, 0.4114], "runtime": 72.78968501091003, "alpha_mse": [0.0, 0.0], "d_mse": [-0.2187, -0.2187], "adv_type": "random_pgd", "dataset": "facebook", "sample_size": 1, "test_ratio": 0.3, "T": 10, "prob_mse": [0.3937, 0.3937], "realization": 9, "beta_mse": [0.0, 0.0], "attack_edge": 10000, "u_mse": [0.8073, 0.8073], "gamma": 0.05, "swap_ratio": 0.01}
{"acc": [0.0, 0.0], "network_size": 8078, "b_mse": [0.1163, 0.1163], "runtime": 107.36129689216614, "alpha_mse": [0.0, 0.0], "d_mse": [0.846, 0.846], "adv_type": "random_pgd", "dataset": "facebook", "sample_size": 1, "test_ratio": 0.3, "T": 10, "prob_mse": [0.1133, 0.1133], "realization": 0, "beta_mse": [0.0, 0.0], "attack_edge": 10000, "u_mse": [0.0377, 0.0377], "gamma": 0.0, "swap_ratio": 0.01}
{"acc": [0.0, 0.0], "network_size": 8078, "b_mse": [0.4087, 0.4087], "runtime": 66.86007905006409, "alpha_mse": [0.0, 0.0], "d_mse": [-0.2216, -0.2216], "adv_type": "random_pgd", "dataset": "facebook", "sample_size": 1, "test_ratio": 0.3, "T": 10, "prob_mse": [0.3954, 0.3954], "realization": 4, "beta_mse": [0.0, 0.0], "attack_edge": 10000, "u_mse": [0.8129, 0.8129], "gamma": 0.07, "swap_ratio": 0.01}
{"acc": [0.0, 0.0], "network_size": 8078, "b_mse": [0.4125, 0.4125], "runtime": 142.518079996109, "alpha_mse": [0.0, 0.0], "d_mse": [-0.2183, -0.2183], "adv_type": "random_pgd", "dataset": "facebook", "sample_size": 1, "test_ratio": 0.3, "T": 10, "prob_mse": [0.392, 0.392], "realization": 0, "beta_mse": [0.0, 0.0], "attack_edge": 10000, "u_mse": [0.8058, 0.8058], "gamma": 0.03, "swap_ratio": 0.01}
{"acc": [0.0, 0.0], "network_size": 8078, "b_mse": [0.4125, 0.4125], "runtime": 145.9949231147766, "alpha_mse": [0.0, 0.0], "d_mse": [-0.2183, -0.2183], "adv_type": "random_pgd", "dataset": "facebook", "sample_size": 1, "test_ratio": 0.3, "T": 10, "prob_mse": [0.392, 0.392], "realization": 0, "beta_mse": [0.0, 0.0], "attack_edge": 10000, "u_mse": [0.8058, 0.8058], "gamma": 0.03, "swap_ratio": 0.01}
{"acc": [0.0, 0.0], "network_size": 8078, "b_mse": [0.1163, 0.1163], "runtime": 147.08241510391235, "alpha_mse": [0.0, 0.0], "d_mse": [0.846, 0.846], "adv_type": "random_pgd", "dataset": "facebook", "sample_size": 1, "test_ratio": 0.3, "T": 10, "prob_mse": [0.1133, 0.1133], "realization": 0, "beta_mse": [0.0, 0.0], "attack_edge": 10000, "u_mse": [0.0377, 0.0377], "gamma": 0.0, "swap_ratio": 0.01}
{"acc": [0.0, 0.0], "network_size": 8078, "b_mse": [0.4112, 0.4112], "runtime": 69.1426100730896, "alpha_mse": [0.0, 0.0], "d_mse": [-0.2228, -0.2228], "adv_type": "random_pgd", "dataset": "facebook", "sample_size": 1, "test_ratio": 0.3, "T": 10, "prob_mse": [0.3945, 0.3945], "realization": 9, "beta_mse": [0.0, 0.0], "attack_edge": 10000, "u_mse": [0.8116, 0.8116], "gamma": 0.07, "swap_ratio": 0.01}
{"acc": [0.0, 0.0], "network_size": 8078, "b_mse": [0.4088, 0.4088], "runtime": 67.62975192070007, "alpha_mse": [0.0, 0.0], "d_mse": [-0.2205, -0.2205], "adv_type": "random_pgd", "dataset": "facebook", "sample_size": 1, "test_ratio": 0.3, "T": 10, "prob_mse": [0.3954, 0.3954], "realization": 4, "beta_mse": [0.0, 0.0], "attack_edge": 10000, "u_mse": [0.8117, 0.8117], "gamma": 0.09, "swap_ratio": 0.01}
{"acc": [0.0, 0.0], "network_size": 8078, "b_mse": [0.119, 0.119], "runtime": 141.7420551776886, "alpha_mse": [0.0, 0.0], "d_mse": [0.8431, 0.8431], "adv_type": "random_pgd", "dataset": "facebook", "sample_size": 1, "test_ratio": 0.3, "T": 10, "prob_mse": [0.1166, 0.1166], "realization": 0, "beta_mse": [0.0, 0.0], "attack_edge": 10000, "u_mse": [0.0379, 0.0379], "gamma": 0.01, "swap_ratio": 0.01}
{"acc": [0.0, 0.0], "network_size": 8078, "b_mse": [0.4109, 0.4109], "runtime": 70.98325085639954, "alpha_mse": [0.0, 0.0], "d_mse": [-0.2221, -0.2221], "adv_type": "random_pgd", "dataset": "facebook", "sample_size": 1, "test_ratio": 0.3, "T": 10, "prob_mse": [0.3942, 0.3942], "realization": 9, "beta_mse": [0.0, 0.0], "attack_edge": 10000, "u_mse": [0.8112, 0.8112], "gamma": 0.09, "swap_ratio": 0.01}
{"acc": [0.0, 0.0], "network_size": 8078, "b_mse": [0.4076, 0.4076], "runtime": 67.28757500648499, "alpha_mse": [0.0, 0.0], "d_mse": [-0.2239, -0.2239], "adv_type": "random_pgd", "dataset": "facebook", "sample_size": 1, "test_ratio": 0.3, "T": 10, "prob_mse": [0.3952, 0.3952], "realization": 4, "beta_mse": [0.0, 0.0], "attack_edge": 10000, "u_mse": [0.8163, 0.8163], "gamma": 0.2, "swap_ratio": 0.01}
{"acc": [0.0, 0.0], "network_size": 8078, "b_mse": [0.4125, 0.4125], "runtime": 181.27196788787842, "alpha_mse": [0.0, 0.0], "d_mse": [-0.2245, -0.2245], "adv_type": "random_pgd", "dataset": "facebook", "sample_size": 1, "test_ratio": 0.3, "T": 10, "prob_mse": [0.3946, 0.3946], "realization": 0, "beta_mse": [0.0, 0.0], "attack_edge": 10000, "u_mse": [0.812, 0.812], "gamma": 0.05, "swap_ratio": 0.01}
{"acc": [0.0, 0.0], "network_size": 8078, "b_mse": [0.4125, 0.4125], "runtime": 185.81202006340027, "alpha_mse": [0.0, 0.0], "d_mse": [-0.2245, -0.2245], "adv_type": "random_pgd", "dataset": "facebook", "sample_size": 1, "test_ratio": 0.3, "T": 10, "prob_mse": [0.3946, 0.3946], "realization": 0, "beta_mse": [0.0, 0.0], "attack_edge": 10000, "u_mse": [0.812, 0.812], "gamma": 0.05, "swap_ratio": 0.01}
{"acc": [0.0, 0.0], "network_size": 8078, "b_mse": [0.4125, 0.4125], "runtime": 180.11318683624268, "alpha_mse": [0.0, 0.0], "d_mse": [-0.2245, -0.2245], "adv_type": "random_pgd", "dataset": "facebook", "sample_size": 1, "test_ratio": 0.3, "T": 10, "prob_mse": [0.3946, 0.3946], "realization": 0, "beta_mse": [0.0, 0.0], "attack_edge": 10000, "u_mse": [0.812, 0.812], "gamma": 0.01, "swap_ratio": 0.01}
{"acc": [0.0, 0.0], "network_size": 8078, "b_mse": [0.4111, 0.4111], "runtime": 69.22741889953613, "alpha_mse": [0.0, 0.0], "d_mse": [-0.2226, -0.2226], "adv_type": "random_pgd", "dataset": "facebook", "sample_size": 1, "test_ratio": 0.3, "T": 10, "prob_mse": [0.3941, 0.3941], "realization": 9, "beta_mse": [0.0, 0.0], "attack_edge": 10000, "u_mse": [0.8115, 0.8115], "gamma": 0.2, "swap_ratio": 0.01}
{"acc": [0.0, 0.0], "network_size": 8078, "b_mse": [0.4078, 0.4078], "runtime": 67.90649390220642, "alpha_mse": [0.0, 0.0], "d_mse": [-0.2155, -0.2155], "adv_type": "random_pgd", "dataset": "facebook", "sample_size": 1, "test_ratio": 0.3, "T": 10, "prob_mse": [0.3946, 0.3946], "realization": 4, "beta_mse": [0.0, 0.0], "attack_edge": 10000, "u_mse": [0.8077, 0.8077], "gamma": 0.3, "swap_ratio": 0.01}
{"acc": [0.0, 0.0], "network_size": 8078, "b_mse": [0.1252, 0.1252], "runtime": 130.7777590751648, "alpha_mse": [0.0, 0.0], "d_mse": [0.8377, 0.8377], "adv_type": "random_pgd", "dataset": "facebook", "sample_size": 1, "test_ratio": 0.3, "T": 10, "prob_mse": [0.1236, 0.1236], "realization": 0, "beta_mse": [0.0, 0.0], "attack_edge": 10000, "u_mse": [0.0371, 0.0371], "gamma": 0.03, "swap_ratio": 0.01}
{"acc": [0.0, 0.0], "network_size": 8078, "b_mse": [0.4109, 0.4109], "runtime": 68.71664214134216, "alpha_mse": [0.0, 0.0], "d_mse": [-0.219, -0.219], "adv_type": "random_pgd", "dataset": "facebook", "sample_size": 1, "test_ratio": 0.3, "T": 10, "prob_mse": [0.394, 0.394], "realization": 9, "beta_mse": [0.0, 0.0], "attack_edge": 10000, "u_mse": [0.8081, 0.8081], "gamma": 0.3, "swap_ratio": 0.01}
{"acc": [0.0, 0.0], "network_size": 8078, "b_mse": [0.4119, 0.4119], "runtime": 144.25724697113037, "alpha_mse": [0.0, 0.0], "d_mse": [-0.2247, -0.2247], "adv_type": "random_pgd", "dataset": "facebook", "sample_size": 1, "test_ratio": 0.3, "T": 10, "prob_mse": [0.395, 0.395], "realization": 0, "beta_mse": [0.0, 0.0], "attack_edge": 10000, "u_mse": [0.8128, 0.8128], "gamma": 0.07, "swap_ratio": 0.01}
{"acc": [0.0, 0.0], "network_size": 8078, "b_mse": [0.4119, 0.4119], "runtime": 149.01636719703674, "alpha_mse": [0.0, 0.0], "d_mse": [-0.2247, -0.2247], "adv_type": "random_pgd", "dataset": "facebook", "sample_size": 1, "test_ratio": 0.3, "T": 10, "prob_mse": [0.395, 0.395], "realization": 0, "beta_mse": [0.0, 0.0], "attack_edge": 10000, "u_mse": [0.8128, 0.8128], "gamma": 0.07, "swap_ratio": 0.01}
{"acc": [0.0, 0.0], "network_size": 8078, "b_mse": [0.4119, 0.4119], "runtime": 148.10254907608032, "alpha_mse": [0.0, 0.0], "d_mse": [-0.2247, -0.2247], "adv_type": "random_pgd", "dataset": "facebook", "sample_size": 1, "test_ratio": 0.3, "T": 10, "prob_mse": [0.395, 0.395], "realization": 0, "beta_mse": [0.0, 0.0], "attack_edge": 10000, "u_mse": [0.8128, 0.8128], "gamma": 0.03, "swap_ratio": 0.01}
{"acc": [0.0, 0.0], "network_size": 8078, "b_mse": [0.4084, 0.4084], "runtime": 69.85078191757202, "alpha_mse": [0.0, 0.0], "d_mse": [-0.2239, -0.2239], "adv_type": "random_pgd", "dataset": "facebook", "sample_size": 1, "test_ratio": 0.3, "T": 10, "prob_mse": [0.3953, 0.3953], "realization": 4, "beta_mse": [0.0, 0.0], "attack_edge": 10000, "u_mse": [0.8155, 0.8155], "gamma": 0.4, "swap_ratio": 0.01}
{"acc": [0.0, 0.0], "network_size": 8078, "b_mse": [0.1333, 0.1333], "runtime": 101.91194987297058, "alpha_mse": [0.0, 0.0], "d_mse": [0.829, 0.829], "adv_type": "random_pgd", "dataset": "facebook", "sample_size": 1, "test_ratio": 0.3, "T": 10, "prob_mse": [0.1322, 0.1322], "realization": 0, "beta_mse": [0.0, 0.0], "attack_edge": 10000, "u_mse": [0.0377, 0.0377], "gamma": 0.05, "swap_ratio": 0.01}
{"acc": [0.0, 0.0], "network_size": 8078, "b_mse": [0.4113, 0.4113], "runtime": 69.41674399375916, "alpha_mse": [0.0, 0.0], "d_mse": [-0.2237, -0.2237], "adv_type": "random_pgd", "dataset": "facebook", "sample_size": 1, "test_ratio": 0.3, "T": 10, "prob_mse": [0.3943, 0.3943], "realization": 9, "beta_mse": [0.0, 0.0], "attack_edge": 10000, "u_mse": [0.8124, 0.8124], "gamma": 0.4, "swap_ratio": 0.01}
{"acc": [0.0, 0.0], "network_size": 8078, "b_mse": [0.4121, 0.4121], "runtime": 125.40041708946228, "alpha_mse": [0.0, 0.0], "d_mse": [-0.2258, -0.2258], "adv_type": "random_pgd", "dataset": "facebook", "sample_size": 1, "test_ratio": 0.3, "T": 10, "prob_mse": [0.3948, 0.3948], "realization": 0, "beta_mse": [0.0, 0.0], "attack_edge": 10000, "u_mse": [0.8137, 0.8137], "gamma": 0.09, "swap_ratio": 0.01}
{"acc": [0.0, 0.0], "network_size": 8078, "b_mse": [0.4092, 0.4092], "runtime": 69.14469289779663, "alpha_mse": [0.0, 0.0], "d_mse": [-0.2148, -0.2148], "adv_type": "random_pgd", "dataset": "facebook", "sample_size": 1, "test_ratio": 0.3, "T": 10, "prob_mse": [0.3941, 0.3941], "realization": 4, "beta_mse": [0.0, 0.0], "attack_edge": 10000, "u_mse": [0.8056, 0.8056], "gamma": 0.5, "swap_ratio": 0.01}
{"acc": [0.0, 0.0], "network_size": 8078, "b_mse": [0.4121, 0.4121], "runtime": 129.5195860862732, "alpha_mse": [0.0, 0.0], "d_mse": [-0.2258, -0.2258], "adv_type": "random_pgd", "dataset": "facebook", "sample_size": 1, "test_ratio": 0.3, "T": 10, "prob_mse": [0.3948, 0.3948], "realization": 0, "beta_mse": [0.0, 0.0], "attack_edge": 10000, "u_mse": [0.8137, 0.8137], "gamma": 0.09, "swap_ratio": 0.01}
{"acc": [0.0, 0.0], "network_size": 8078, "b_mse": [0.4121, 0.4121], "runtime": 130.33950781822205, "alpha_mse": [0.0, 0.0], "d_mse": [-0.2258, -0.2258], "adv_type": "random_pgd", "dataset": "facebook", "sample_size": 1, "test_ratio": 0.3, "T": 10, "prob_mse": [0.3948, 0.3948], "realization": 0, "beta_mse": [0.0, 0.0], "attack_edge": 10000, "u_mse": [0.8137, 0.8137], "gamma": 0.05, "swap_ratio": 0.01}
{"acc": [0.0, 0.0], "network_size": 8078, "b_mse": [0.1451, 0.1451], "runtime": 94.06522512435913, "alpha_mse": [0.0, 0.0], "d_mse": [0.8101, 0.8101], "adv_type": "random_pgd", "dataset": "facebook", "sample_size": 1, "test_ratio": 0.3, "T": 10, "prob_mse": [0.1407, 0.1407], "realization": 0, "beta_mse": [0.0, 0.0], "attack_edge": 10000, "u_mse": [0.0448, 0.0448], "gamma": 0.07, "swap_ratio": 0.01}
{"acc": [0.0, 0.0], "network_size": 8078, "b_mse": [0.4115, 0.4115], "runtime": 67.60284185409546, "alpha_mse": [0.0, 0.0], "d_mse": [-0.2172, -0.2172], "adv_type": "random_pgd", "dataset": "facebook", "sample_size": 1, "test_ratio": 0.3, "T": 10, "prob_mse": [0.3929, 0.3929], "realization": 9, "beta_mse": [0.0, 0.0], "attack_edge": 10000, "u_mse": [0.8057, 0.8057], "gamma": 0.5, "swap_ratio": 0.01}
{"acc": [0.0, 0.0], "network_size": 8078, "b_mse": [0.412, 0.412], "runtime": 117.91788101196289, "alpha_mse": [0.0, 0.0], "d_mse": [-0.2238, -0.2238], "adv_type": "random_pgd", "dataset": "facebook", "sample_size": 1, "test_ratio": 0.3, "T": 10, "prob_mse": [0.3946, 0.3946], "realization": 0, "beta_mse": [0.0, 0.0], "attack_edge": 10000, "u_mse": [0.8118, 0.8118], "gamma": 0.2, "swap_ratio": 0.01}
{"acc": [0.0, 0.0], "network_size": 8078, "b_mse": [0.412, 0.412], "runtime": 124.61469292640686, "alpha_mse": [0.0, 0.0], "d_mse": [-0.2238, -0.2238], "adv_type": "random_pgd", "dataset": "facebook", "sample_size": 1, "test_ratio": 0.3, "T": 10, "prob_mse": [0.3946, 0.3946], "realization": 0, "beta_mse": [0.0, 0.0], "attack_edge": 10000, "u_mse": [0.8118, 0.8118], "gamma": 0.2, "swap_ratio": 0.01}
{"acc": [0.0, 0.0], "network_size": 8078, "b_mse": [0.412, 0.412], "runtime": 123.86447405815125, "alpha_mse": [0.0, 0.0], "d_mse": [-0.2238, -0.2238], "adv_type": "random_pgd", "dataset": "facebook", "sample_size": 1, "test_ratio": 0.3, "T": 10, "prob_mse": [0.3946, 0.3946], "realization": 0, "beta_mse": [0.0, 0.0], "attack_edge": 10000, "u_mse": [0.8118, 0.8118], "gamma": 0.07, "swap_ratio": 0.01}
{"acc": [0.0, 0.0], "network_size": 8078, "b_mse": [0.1548, 0.1548], "runtime": 96.47543597221375, "alpha_mse": [0.0, 0.0], "d_mse": [0.7992, 0.7992], "adv_type": "random_pgd", "dataset": "facebook", "sample_size": 1, "test_ratio": 0.3, "T": 10, "prob_mse": [0.151, 0.151], "realization": 0, "beta_mse": [0.0, 0.0], "attack_edge": 10000, "u_mse": [0.046, 0.046], "gamma": 0.09, "swap_ratio": 0.01}
{"acc": [0.0, 0.0], "network_size": 8078, "b_mse": [0.4126, 0.4126], "runtime": 113.46552586555481, "alpha_mse": [0.0, 0.0], "d_mse": [-0.219, -0.219], "adv_type": "random_pgd", "dataset": "facebook", "sample_size": 1, "test_ratio": 0.3, "T": 10, "prob_mse": [0.3934, 0.3934], "realization": 0, "beta_mse": [0.0, 0.0], "attack_edge": 10000, "u_mse": [0.8064, 0.8064], "gamma": 0.3, "swap_ratio": 0.01}
{"acc": [0.0, 0.0], "network_size": 8078, "b_mse": [0.4126, 0.4126], "runtime": 119.2797360420227, "alpha_mse": [0.0, 0.0], "d_mse": [-0.219, -0.219], "adv_type": "random_pgd", "dataset": "facebook", "sample_size": 1, "test_ratio": 0.3, "T": 10, "prob_mse": [0.3934, 0.3934], "realization": 0, "beta_mse": [0.0, 0.0], "attack_edge": 10000, "u_mse": [0.8064, 0.8064], "gamma": 0.3, "swap_ratio": 0.01}
{"acc": [0.0, 0.0], "network_size": 8078, "b_mse": [0.4126, 0.4126], "runtime": 119.88829708099365, "alpha_mse": [0.0, 0.0], "d_mse": [-0.219, -0.219], "adv_type": "random_pgd", "dataset": "facebook", "sample_size": 1, "test_ratio": 0.3, "T": 10, "prob_mse": [0.3934, 0.3934], "realization": 0, "beta_mse": [0.0, 0.0], "attack_edge": 10000, "u_mse": [0.8064, 0.8064], "gamma": 0.09, "swap_ratio": 0.01}
{"acc": [0.0, 0.0], "network_size": 8078, "b_mse": [0.2089, 0.2089], "runtime": 94.20013093948364, "alpha_mse": [0.0, 0.0], "d_mse": [0.7375, 0.7375], "adv_type": "random_pgd", "dataset": "facebook", "sample_size": 1, "test_ratio": 0.3, "T": 10, "prob_mse": [0.197, 0.197], "realization": 0, "beta_mse": [0.0, 0.0], "attack_edge": 10000, "u_mse": [0.0536, 0.0536], "gamma": 0.2, "swap_ratio": 0.01}
{"acc": [0.0, 0.0], "network_size": 8078, "b_mse": [0.4123, 0.4123], "runtime": 112.00935292243958, "alpha_mse": [0.0, 0.0], "d_mse": [-0.2268, -0.2268], "adv_type": "random_pgd", "dataset": "facebook", "sample_size": 1, "test_ratio": 0.3, "T": 10, "prob_mse": [0.3951, 0.3951], "realization": 0, "beta_mse": [0.0, 0.0], "attack_edge": 10000, "u_mse": [0.8145, 0.8145], "gamma": 0.4, "swap_ratio": 0.01}
{"acc": [0.0, 0.0], "network_size": 8078, "b_mse": [0.4123, 0.4123], "runtime": 119.42885994911194, "alpha_mse": [0.0, 0.0], "d_mse": [-0.2268, -0.2268], "adv_type": "random_pgd", "dataset": "facebook", "sample_size": 1, "test_ratio": 0.3, "T": 10, "prob_mse": [0.3951, 0.3951], "realization": 0, "beta_mse": [0.0, 0.0], "attack_edge": 10000, "u_mse": [0.8145, 0.8145], "gamma": 0.4, "swap_ratio": 0.01}
{"acc": [0.0, 0.0], "network_size": 8078, "b_mse": [0.4123, 0.4123], "runtime": 119.5790798664093, "alpha_mse": [0.0, 0.0], "d_mse": [-0.2268, -0.2268], "adv_type": "random_pgd", "dataset": "facebook", "sample_size": 1, "test_ratio": 0.3, "T": 10, "prob_mse": [0.3951, 0.3951], "realization": 0, "beta_mse": [0.0, 0.0], "attack_edge": 10000, "u_mse": [0.8145, 0.8145], "gamma": 0.2, "swap_ratio": 0.01}
{"acc": [0.0, 0.0], "network_size": 8078, "b_mse": [0.2681, 0.2681], "runtime": 97.45566201210022, "alpha_mse": [0.0, 0.0], "d_mse": [0.6768, 0.6768], "adv_type": "random_pgd", "dataset": "facebook", "sample_size": 1, "test_ratio": 0.3, "T": 10, "prob_mse": [0.2656, 0.2656], "realization": 0, "beta_mse": [0.0, 0.0], "attack_edge": 10000, "u_mse": [0.0551, 0.0551], "gamma": 0.3, "swap_ratio": 0.01}
{"acc": [0.0, 0.0], "network_size": 8078, "b_mse": [0.4126, 0.4126], "runtime": 112.05842685699463, "alpha_mse": [0.0, 0.0], "d_mse": [-0.2259, -0.2259], "adv_type": "random_pgd", "dataset": "facebook", "sample_size": 1, "test_ratio": 0.3, "T": 10, "prob_mse": [0.3952, 0.3952], "realization": 0, "beta_mse": [0.0, 0.0], "attack_edge": 10000, "u_mse": [0.8133, 0.8133], "gamma": 0.5, "swap_ratio": 0.01}
{"acc": [0.0, 0.0], "network_size": 8078, "b_mse": [0.4126, 0.4126], "runtime": 117.5640459060669, "alpha_mse": [0.0, 0.0], "d_mse": [-0.2259, -0.2259], "adv_type": "random_pgd", "dataset": "facebook", "sample_size": 1, "test_ratio": 0.3, "T": 10, "prob_mse": [0.3952, 0.3952], "realization": 0, "beta_mse": [0.0, 0.0], "attack_edge": 10000, "u_mse": [0.8133, 0.8133], "gamma": 0.5, "swap_ratio": 0.01}
{"acc": [0.0, 0.0], "network_size": 8078, "b_mse": [0.4126, 0.4126], "runtime": 119.94016408920288, "alpha_mse": [0.0, 0.0], "d_mse": [-0.2259, -0.2259], "adv_type": "random_pgd", "dataset": "facebook", "sample_size": 1, "test_ratio": 0.3, "T": 10, "prob_mse": [0.3952, 0.3952], "realization": 0, "beta_mse": [0.0, 0.0], "attack_edge": 10000, "u_mse": [0.8133, 0.8133], "gamma": 0.3, "swap_ratio": 0.01}
{"acc": [0.0, 0.0], "network_size": 8078, "b_mse": [0.3333, 0.3333], "runtime": 99.43646693229675, "alpha_mse": [0.0, 0.0], "d_mse": [0.6212, 0.6212], "adv_type": "random_pgd", "dataset": "facebook", "sample_size": 1, "test_ratio": 0.3, "T": 10, "prob_mse": [0.3278, 0.3278], "realization": 0, "beta_mse": [0.0, 0.0], "attack_edge": 10000, "u_mse": [0.0455, 0.0455], "gamma": 0.4, "swap_ratio": 0.01}
{"acc": [0.0, 0.0], "network_size": 8078, "b_mse": [0.4126, 0.4126], "runtime": 75.78909087181091, "alpha_mse": [0.0, 0.0], "d_mse": [-0.2244, -0.2244], "adv_type": "random_pgd", "dataset": "facebook", "sample_size": 1, "test_ratio": 0.3, "T": 10, "prob_mse": [0.3944, 0.3944], "realization": 0, "beta_mse": [0.0, 0.0], "attack_edge": 10000, "u_mse": [0.8118, 0.8118], "gamma": 0.4, "swap_ratio": 0.01}
{"acc": [0.0, 0.0], "network_size": 8078, "b_mse": [0.3973, 0.3973], "runtime": 79.17647504806519, "alpha_mse": [0.0, 0.0], "d_mse": [0.5668, 0.5668], "adv_type": "random_pgd", "dataset": "facebook", "sample_size": 1, "test_ratio": 0.3, "T": 10, "prob_mse": [0.3977, 0.3977], "realization": 0, "beta_mse": [0.0, 0.0], "attack_edge": 10000, "u_mse": [0.0359, 0.0359], "gamma": 0.5, "swap_ratio": 0.01}
{"acc": [0.0, 0.0], "network_size": 8078, "b_mse": [0.4126, 0.4126], "runtime": 65.8860719203949, "alpha_mse": [0.0, 0.0], "d_mse": [-0.2245, -0.2245], "adv_type": "random_pgd", "dataset": "facebook", "sample_size": 1, "test_ratio": 0.3, "T": 10, "prob_mse": [0.3945, 0.3945], "realization": 0, "beta_mse": [0.0, 0.0], "attack_edge": 10000, "u_mse": [0.8119, 0.8119], "gamma": 0.5, "swap_ratio": 0.01}
